mcp_client_whby2/__init__.py
mcp_client_whby2/__main__.py
mcp_client_whby2/server.py
mcp_client_whby2-0.1.0.dist-info/METADATA
mcp_client_whby2-0.1.0.dist-info/WHEEL
mcp_client_whby2-0.1.0.dist-info/entry_points.txt
mcp_client_whby2-0.1.0.dist-info/top_level.txt
mcp_client_whby2-0.1.0.dist-info/RECORD
