Metadata-Version: 2.4
Name: mcp_client_whby2
Version: 0.1.0
Summary: Add your description here
Requires-Python: >=3.12
Requires-Dist: httpx>=0.28.1
Requires-Dist: mcp>=1.9.4
Requires-Dist: openai>=1.91.0
Requires-Dist: python-dotenv>=1.1.1
